MANIFEST.in
README.md
setup.py
stresser/__init__.py
stresser.egg-info/PKG-INFO
stresser.egg-info/SOURCES.txt
stresser.egg-info/dependency_links.txt
stresser.egg-info/entry_points.txt
stresser.egg-info/requires.txt
stresser.egg-info/top_level.txt
stresser/commander/__init__.py
stresser/commander/cli.py
stresser/soldier/__init__.py
stresser/soldier/cli.py
stresser/soldier/task.py