Metadata-Version: 1.1
Name: stresser
Version: 0.1.3
Summary: A large-scale stress testing framework.
Home-page: https://github.com/kfei/stresser
Author: Lin, Ke-fei
Author-email: kfei@kfei.net
License: MIT
Keywords: stress,test,automation,framework,sikuli
Platform: UNKNOWN
Classifier: Development Status :: 5 - Production/Stable
Classifier: Intended Audience :: Developers
Classifier: License :: OSI Approved :: MIT License
Classifier: Topic :: Software Development :: Testing
Classifier: Operating System :: OS Independent
Classifier: Programming Language :: Python :: 2.7
